<?xml version="1.0" encoding="utf-8" ?>

<alfresco-config>
    <!-- Document Library config section -->
    <config evaluator="string-compare" condition="DocumentLibrary">
        <aspects>
            <!-- Aspects that a user can see -->
            <visible>
				<aspect name="rb:relevante" />
				<aspect name="rb:revisable" />
				<aspect name="rb:oficioSaliente" />
			<!--
                <aspect name="sc:webable" />
                <aspect name="sc:productRelated" />            
            -->
			</visible>
            <!-- Aspects that a user can add. Same as "visible" if left empty -->
            <addable>
            </addable>
            <!-- Aspects that a user can remove. Same as "visible" if left empty -->
            <removeable>
            </removeable>
        </aspects>
        <types>
             <type name="cm:content">
                <subtype name="rb:doc" />
                <subtype name="rb:oficio" />
             </type>
             <type name="rb:doc">
                <subtype name="rb:oficio" />
             </type>
        </types>		
	</config>
	   <!-- extracted from cm:content type (existing nodes) -->
   <config evaluator="node-type" condition="rb:oficio">
      <forms>
         <!-- Default form configuration for the rb:oficio type -->
         <form>
            <field-visibility>
               <show id="cm:name" />
               <show id="cm:title" force="true" />
               <show id="cm:description" force="true" />
               <show id="mimetype" />
               <show id="cm:author" force="true" />
               <show id="size" for-mode="view" />
               <show id="cm:creator" for-mode="view" />
               <show id="cm:created" for-mode="view" />
               <show id="cm:modifier" for-mode="view" />
               <show id="cm:modified" for-mode="view" />
               
               <!-- tags and categories -->
               <show id="cm:taggable" for-mode="edit" force="true" />
               <show id="cm:categories" />
               
			   <!-- atributos de rb:oficio -->
				<show id="rb:tema" />
				<show id="rb:destinatario" />
				<show id="rb:remitente" />
				<show id="rb:radicado_ext" />
				<show id="rb:fecha_radicado" />
				<show id="rb:respuesta_req" />
				<show id="rb:fecha_resp" />
				<show id="rb:area_resp" />
				<!--
				<show id="rb:persona_resp" />
				-->
				<show id="rb:respondida" />
				<show id="rb:personaResp" />
				<!-- atributos de aspects si son aplicados -->
				<show id="rb:relevancia" />
				<show id="rb:revisado" />
				<show id="rb:borradorContOk" />
				<show id="rb:borradorJurOk" />
				<show id="rb:aprobado" />
				<show id="rb:firmado" />
				<show id="rb:radicado" />
				
			   
               <!-- cm:dublincore aspect -->
               <show id="cm:publisher"/>
               <show id="cm:contributor"/>
               <show id="cm:type"/>
               <show id="cm:identifier"/>
               <show id="cm:dcsource"/>
               <show id="cm:coverage"/>
               <show id="cm:rights"/>
               <show id="cm:subject"/>
               
               <!-- cm:complianceable aspect -->
               <show id="cm:removeAfter" />
               
               <!-- cm:effectivity aspect -->
               <show id="cm:from"/>
               <show id="cm:to"/>
               
               <!--  cm:summarizable aspect -->
               <show id="cm:summary" />
               
               <!-- cm:translatable aspect -->
               <show id="cm:translations" />
               
               <!-- cm:localizable aspect -->
               <show id="cm:locale" />
               
               <!-- cm:ownable aspect -->
               <show id="cm:owner" />
               
               <!-- cm:attachable aspect -->
               <show id="cm:attachments" />
               
               <!-- cm:emailed aspect -->
               <show id="cm:originator" />
               <show id="cm:addressee" />
               <show id="cm:addressees" />
               <show id="cm:sentdate" />
               <show id="cm:subjectline" />
               
               <!-- exif:exif aspect -->
               <show id="exif:dateTimeOriginal" />
               <show id="exif:pixelXDimension" />
               <show id="exif:pixelYDimension" />
               <show id="exif:exposureTime" />
               <show id="exif:fNumber" />
               <show id="exif:flash" />
               <show id="exif:focalLength" />
               <show id="exif:isoSpeedRatings" />
               <show id="exif:manufacturer" />
               <show id="exif:model" />
               <show id="exif:software" />
               <show id="exif:orientation" />
               <show id="exif:xResolution" />
               <show id="exif:yResolution" />
               <show id="exif:resolutionUnit" />

               <!-- audio:audio aspect -->
               <show id="audio:album" />
               <show id="audio:artist" />
               <show id="audio:composer" />
               <show id="audio:engineer" />
               <show id="audio:genre" />
               <show id="audio:trackNumber" />
               <show id="audio:releaseDate" />
               <show id="audio:sampleRate" />
               <show id="audio:sampleType" />
               <show id="audio:channelType" />
               <show id="audio:compressor" />
               
               <!-- cm:indexControl aspect -->
               <show id="cm:isIndexed" />
               <show id="cm:isContentIndexed" />
               
               <!-- cm:geographic aspect -->
               <show id="cm:latitude" />
               <show id="cm:longitude" />
			   
			   <!-- rb:oficio -->
			   <show id="rb:documentosRelacionados" />
			   
            </field-visibility>
            <appearance>
				<set id="datos_oficio" appearance="panel" label-id="panel.rb_datosOficio" />
				<set id="oficio_saliente" appearance="panel" label-id="panel.rb_oficioSaliente" />
               <field id="cm:name">
                 <control>
                    <control-param name="maxLength">255</control-param>
                 </control>
               </field>
               <field id="cm:title">
                  <control template="/org/alfresco/components/form/controls/textfield.ftl" />
               </field>
               <field id="cm:description">
                  <control>
                     <control-param name="activateLinks">true</control-param>
                  </control>
               </field>
               <field id="mimetype">
                  <control template="/org/alfresco/components/form/controls/mimetype.ftl" />
               </field>
               <field id="size">
                  <control template="/org/alfresco/components/form/controls/size.ftl" />
               </field>
               <field id="cm:taggable">
                  <control>
                     <control-param name="compactMode">true</control-param>
                     <control-param name="params">aspect=cm:taggable</control-param>
                     <control-param name="createNewItemUri">/api/tag/workspace/SpacesStore</control-param>
                     <control-param name="createNewItemIcon">tag</control-param>
                  </control>
               </field>
               <field id="cm:categories">
                  <control>
                     <control-param name="compactMode">true</control-param>
                  </control>
               </field>
			   
			   	<!-- atributos de rb:oficio -->
				<field id="rb:tema" label-id="prop.rb_tema" set="datos_oficio" />
				<field id="rb:destinatario" label-id="prop.rb_destinatario" set="datos_oficio" >
					<control template="/org/alfresco/components/form/controls/category.ftl"> 
					<!-- Configuramos la categorìa para que se inicie en el nodo de "Entidades" -->
						<control-param name="parentNodeRef">workspace://SpacesStore/ab0e64a2-96a4-4c09-b316-d97b280a6ab3</control-param>
					</control>
				</field>
				<field id="rb:remitente" label-id="prop.rb_remitente" set="datos_oficio"  >
					<control template="/org/alfresco/components/form/controls/category.ftl"> 
						<control-param name="parentNodeRef">workspace://SpacesStore/ab0e64a2-96a4-4c09-b316-d97b280a6ab3</control-param>
					</control>
				</field>
				<field id="rb:radicado_ext" label-id="prop.rb_radicado_ext" set="datos_oficio"  />
				<field id="rb:fecha_radicado" label-id="prop.rb_fecha_radicado" set="datos_oficio"  />
				<field id="rb:respuesta_req" label-id="prop.rb_respuesta_req" set="datos_oficio"  />
				<field id="rb:fecha_resp" label-id="prop.rb_fecha_resp" set="datos_oficio"  />
				<field id="rb:area_resp" label-id="prop.rb_area_resp" set="datos_oficio" >
					<control template="/org/alfresco/components/form/controls/category.ftl"> 
					<!-- Configuramos la categorìa para que se inicie en el nodo de "Areas de Empresa" -->
						<control-param name="parentNodeRef">workspace://SpacesStore/7b6839e0-4b90-477f-b5aa-de44e415a70a</control-param>
					</control>
				</field>
				<!--
				<field id="rb:persona_resp" label-id="prop.rb_persona_resp" set="datos_oficio"  />
				-->
				<field id="rb:respondida" label-id="prop.rb_respondida" set="datos_oficio"  />
				<field id="rb:personaResp" label-id="assoc.rb_personaResp" set="datos_oficio"  />
				<field id="rb:relevancia" label-id="prop.rb_relevancia" set="datos_oficio"  >
						<control template="/org/alfresco/components/form/controls/selectone.ftl" >
							<control-param name="options">1|{label.alta},2|{label.media},3|{label.baja}</control-param>
						</control>
				</field>		
				<field id="rb:revisado" label-id="prop.rb_revisado" set="datos_oficio"  />
				<field id="rb:documentosRelacionados" label-id="assoc.rb_documentosRelacionados" set="datos_oficio"  />
				
				<field id="rb:borradorContOk" label-id="prop.rb_borradorContOk" set="oficio_saliente" />
				<field id="rb:borradorJurOk" label-id="prop.rb_borradorJurOk" set="oficio_saliente" />
				<field id="rb:aprobado" label-id="prop.rb_aprobado" set="oficio_saliente" />
				<field id="rb:firmado" label-id="prop.rb_firmado" set="oficio_saliente" />
				<field id="rb:radicado" label-id="prop.rb_radicado" set="oficio_saliente" />
			   
               <field id="cm:originator" read-only="true" />
               <field id="cm:addressee" read-only="true" />
               <field id="cm:addressees" read-only="true" />
               <field id="cm:sentdate" read-only="true" />
               <field id="cm:subjectline" read-only="true" />

            </appearance>
         </form>

         <!-- Document Library pop-up Edit Metadata form -->
         <form id="doclib-simple-metadata">
            <field-visibility>
               <show id="cm:name" />
               <show id="cm:title" force="true" />
               <show id="cm:description" force="true" />
               <!-- tags and categories -->
               <show id="cm:taggable" for-mode="edit" force="true" />
               <show id="cm:categories" />
			   
				<!-- atributos de rb:oficio -->
				<show id="rb:tema" />
				<show id="rb:destinatario" />
				<show id="rb:remitente" />
				<show id="rb:radicado_ext" />
				<show id="rb:fecha_radicado" />
				<show id="rb:respuesta_req" />
				<show id="rb:fecha_resp" />
				<show id="rb:area_resp" />
				<!--
				<show id="rb:persona_resp" />
				-->
				<show id="rb:respondida" />
				<show id="rb:personaResp" />
				<!-- atributos de aspects si son aplicados -->
				<show id="rb:relevancia" />
				<show id="rb:revisado" />
				<show id="rb:borradorContOk" />
				<show id="rb:borradorJurOk" />
				<show id="rb:aprobado" />
				<show id="rb:firmado" />
				<show id="rb:radicado" />
			   
			   <!-- rb:oficio -->
			   <show id="rb:documentosRelacionados" />
			   
            </field-visibility>
            <edit-form template="../documentlibrary/forms/doclib-simple-metadata.ftl" />
            <appearance>
				<set id="datos_oficio" appearance="panel" label-id="panel.rb_datosOficio" />
               <field id="cm:name">
                 <control>
                    <control-param name="maxLength">255</control-param>
                 </control>
               </field>
               <field id="cm:title">
                  <control template="/org/alfresco/components/form/controls/textfield.ftl" />
               </field>
               <field id="cm:description">
                  <control>
                     <control-param name="activateLinks">true</control-param>
                  </control>
               </field>
               <field id="cm:taggable">
                  <control>
                     <control-param name="compactMode">true</control-param>
                     <control-param name="params">aspect=cm:taggable</control-param>
                     <control-param name="createNewItemUri">/api/tag/workspace/SpacesStore</control-param>
                     <control-param name="createNewItemIcon">tag</control-param>
                  </control>
               </field>
               <field id="cm:categories">
                  <control>
                     <control-param name="compactMode">true</control-param>
                  </control>
               </field>
			   	
				<!-- atributos de rb:oficio -->
				<field id="rb:tema" label-id="prop.rb_tema" set="datos_oficio"  />
				<field id="rb:destinatario" label-id="prop.rb_destinatario" set="datos_oficio"  >
					<control template="/org/alfresco/components/form/controls/category.ftl"> 
					<!-- Configuramos la categorìa para que se inicie en el nodo de "Entidades" -->
						<control-param name="parentNodeRef">workspace://SpacesStore/ab0e64a2-96a4-4c09-b316-d97b280a6ab3</control-param>
					</control>
				</field>
				<field id="rb:remitente" label-id="prop.rb_remitente" set="datos_oficio"  >
					<control template="/org/alfresco/components/form/controls/category.ftl"> 
						<control-param name="parentNodeRef">workspace://SpacesStore/ab0e64a2-96a4-4c09-b316-d97b280a6ab3</control-param>
					</control>
				</field>
				<field id="rb:radicado_ext" label-id="prop.rb_radicado_ext" set="datos_oficio"  />
				<field id="rb:fecha_radicado" label-id="prop.rb_fecha_radicado" set="datos_oficio"  />
				<field id="rb:respuesta_req" label-id="prop.rb_respuesta_req" set="datos_oficio"  />
				<field id="rb:fecha_resp" label-id="prop.rb_fecha_resp" set="datos_oficio"  />
				<!--
				<field id="rb:area_resp" label-id="prop.rb_area_resp" set="datos_oficio"  />
				-->
				<field id="rb:area_resp" label-id="prop.rb_area_resp" set="datos_oficio" >
					<control template="/org/alfresco/components/form/controls/category.ftl"> 
					<!-- Configuramos la categorìa para que se inicie en el nodo de "Areas de Empresa" -->
						<control-param name="parentNodeRef">workspace://SpacesStore/7b6839e0-4b90-477f-b5aa-de44e415a70a</control-param>
					</control>
				</field>
				<!--
				<field id="rb:persona_resp" label-id="prop.rb_persona_resp" set="datos_oficio"  />
				-->
				<field id="rb:respondida" label-id="prop.rb_respondida" set="datos_oficio"  />
				<field id="rb:personaResp" label-id="assoc.rb_personaResp" set="datos_oficio"  />
				<field id="rb:relevancia" label-id="prop.rb_relevancia" set="datos_oficio"  >
						<control template="/org/alfresco/components/form/controls/selectone.ftl" >
							<control-param name="options">1|{label.alta},2|{label.media},3|{label.baja}</control-param>
						</control>
				</field>		
				<field id="rb:revisado" label-id="prop.rb_revisado" set="datos_oficio"  />
							   
				<field id="rb:documentosRelacionados" label-id="assoc.rb_documentosRelacionados" set="datos_oficio"  />
				<field id="rb:borradorContOk" label-id="prop.rb_borradorContOk" set="oficio_saliente" />
				<field id="rb:borradorJurOk" label-id="prop.rb_borradorJurOk" set="oficio_saliente" />
				<field id="rb:aprobado" label-id="prop.rb_aprobado" set="oficio_saliente" />
				<field id="rb:firmado" label-id="prop.rb_firmado" set="oficio_saliente" />
				<field id="rb:radicado" label-id="prop.rb_radicado" set="oficio_saliente" />
            </appearance>
         </form>
         
         <!-- Document Library Inline Edit form -->
         <form id="doclib-inline-edit">
            <field-visibility>
               <show id="cm:name" />
               <show id="cm:title" force="true" />
               <show id="cm:description" force="true" />
               <show id="cm:content" force="true" />
				
				<!-- atributos de rb:oficio -->
				<show id="rb:tema" />
				<show id="rb:destinatario" />
				<show id="rb:remitente" />
				<show id="rb:radicado_ext" />
				<show id="rb:fecha_radicado" />
				<show id="rb:respuesta_req" />
				<show id="rb:fecha_resp" />
				<show id="rb:area_resp" />
				<!--
				<show id="rb:persona_resp" />
				-->
				<show id="rb:respondida" />
				<show id="rb:personaResp" />
				<!-- atributos de aspects si son aplicados -->
				<show id="rb:relevancia" />
				<show id="rb:revisado" />
				<show id="rb:borradorContOk" />
				<show id="rb:borradorJurOk" />
				<show id="rb:aprobado" />
				<show id="rb:firmado" />
				<show id="rb:radicado" />
				
			   <!-- rb:oficio -->
			   <show id="rb:documentosRelacionados" />				
			</field-visibility>
            <appearance>
				<set id="datos_oficio" appearance="panel" label-id="panel.rb_datosOficio" />
               <field id="cm:name">
                 <control>
                    <control-param name="maxLength">255</control-param>
                 </control>
               </field>
               <field id="cm:title">
                  <control template="/org/alfresco/components/form/controls/textfield.ftl" />
               </field>
               <field id="cm:content">
                  <control>
                     <control-param name="editorAppearance">explorer</control-param>
                     <control-param name="forceEditor">true</control-param>
                  </control>
               </field>
			   
			   			   			   <!-- atributos de rb:oficio -->
				<field id="rb:tema" label-id="prop.rb_tema" set="datos_oficio"  />
				<field id="rb:destinatario" label-id="prop.rb_destinatario" set="datos_oficio"  >
					<control template="/org/alfresco/components/form/controls/category.ftl"> 
					<!-- Configuramos la categorìa para que se inicie en el nodo de "Entidades" -->
						<control-param name="parentNodeRef">workspace://SpacesStore/ab0e64a2-96a4-4c09-b316-d97b280a6ab3</control-param>
					</control>
				</field>
				<field id="rb:remitente" label-id="prop.rb_remitente" set="datos_oficio"  >
					<control template="/org/alfresco/components/form/controls/category.ftl"> 
						<control-param name="parentNodeRef">workspace://SpacesStore/ab0e64a2-96a4-4c09-b316-d97b280a6ab3</control-param>
					</control>
				</field>
				<field id="rb:radicado_ext" label-id="prop.rb_radicado_ext" set="datos_oficio"  />
				<field id="rb:fecha_radicado" label-id="prop.rb_fecha_radicado" set="datos_oficio"  />
				<field id="rb:respuesta_req" label-id="prop.rb_respuesta_req" set="datos_oficio"  />
				<field id="rb:fecha_resp" label-id="prop.rb_fecha_resp" set="datos_oficio"  />
				<!--
				<field id="rb:area_resp" label-id="prop.rb_area_resp" set="datos_oficio"  />
				-->
				<field id="rb:area_resp" label-id="prop.rb_area_resp" set="datos_oficio" >
					<control template="/org/alfresco/components/form/controls/category.ftl"> 
					<!-- Configuramos la categorìa para que se inicie en el nodo de "Areas de Empresa" -->
						<control-param name="parentNodeRef">workspace://SpacesStore/7b6839e0-4b90-477f-b5aa-de44e415a70a</control-param>
					</control>
				</field>
				<!--
				<field id="rb:persona_resp" label-id="prop.rb_persona_resp" set="datos_oficio"  />
				-->
				<field id="rb:respondida" label-id="prop.rb_respondida" set="datos_oficio"  />
				
				<field id="rb:personaResp" label-id="assoc.rb_personaResp" set="datos_oficio"  />
				<field id="rb:relevancia" label-id="prop.rb_relevancia" set="datos_oficio"  >
						<control template="/org/alfresco/components/form/controls/selectone.ftl" >
							<control-param name="options">1|{label.alta},2|{label.media},3|{label.baja}</control-param>
						</control>
				</field>		
				<field id="rb:revisado" label-id="prop.rb_revisado" set="datos_oficio"  />
							   
				<field id="rb:documentosRelacionados" label-id="assoc.rb_documentosRelacionados" set="datos_oficio"  />
				<field id="rb:borradorContOk" label-id="prop.rb_borradorContOk" set="oficio_saliente" />
				<field id="rb:borradorJurOk" label-id="prop.rb_borradorJurOk" set="oficio_saliente" />
				<field id="rb:aprobado" label-id="prop.rb_aprobado" set="oficio_saliente" />
				<field id="rb:firmado" label-id="prop.rb_firmado" set="oficio_saliente" />
				<field id="rb:radicado" label-id="prop.rb_radicado" set="oficio_saliente" />
            </appearance>
         </form>
      </forms>
   </config>
   
	<config replace="true" evaluator="string-compare" condition="AdvancedSearch">
		<advanced-search>
			<!-- Forms for the advanced search type list -->
			<forms>
				<form labelId="search.form.label.cm_content" descriptionId="search.form.desc.cm_content">cm:content</form>
				<form labelId="search.form.label.cm_folder" descriptionId="search.form.desc.cm_folder">cm:folder</form>            
				<form labelId="type.rb_oficio" descriptionId="search.form.desc.rb_oficio">rb:oficio</form>
			</forms>
		</advanced-search>
	</config>
	
					
	<!-- rb:oficio type (new nodes) -->
	<config evaluator="model-type" condition="rb:oficio">
		<forms>
		<!-- Search form -->
			<form id="search">
				<field-visibility>
					<show id="cm:name" />
					<show id="cm:title" force="true" />
					<show id="cm:description" force="true" />
					<show id="mimetype" />
					<show id="cm:modified" />
					<show id="cm:modifier" />
					<!-- rb:oficio -->
					<show id="rb:tema" />
					<show id="rb:destinatario" />
					<show id="rb:remitente" />
					<show id="rb:radicado_ext" />
					<show id="rb:fecha_radicado" />
					<show id="rb:respuesta_req" />
					<show id="rb:fecha_resp" />
					<show id="rb:area_resp" />
					<!--
					<show id="rb:persona_resp" />
					-->
					<show id="rb:respondida" />
					<show id="rb:personaResp" />
					<!-- atributos de aspects si son aplicados -->
					<show id="rb:relevancia" />
					<show id="rb:revisado" />
					
				</field-visibility>
				<appearance>
					<set id="datos_oficio" appearance="panel" label-id="panel.rb_datosOficio" />
					<field id="mimetype">
						<control template="/org/alfresco/components/form/controls/mimetype.ftl" />
					</field>
					<field id="cm:modifier">
						<control>
							<control-param name="forceEditable">true</control-param>
						</control>
					</field>
					<field id="cm:modified">
						<control template="/org/alfresco/components/form/controls/daterange.ftl" />
					</field>
					<!-- rb:oficio -->
					<field id="rb:tema" label-id="prop.rb_tema" set="datos_oficio" >
						<control template="/org/alfresco/components/form/controls/textfield.ftl" />
					</field>
					<field id="rb:destinatario" label-id="prop.rb_destinatario" set="datos_oficio" >
						<control template="/org/alfresco/components/form/controls/category.ftl"> 
						<!-- Configuramos la categorìa para que se inicie en el nodo de "Entidades" -->
							<control-param name="parentNodeRef">workspace://SpacesStore/ab0e64a2-96a4-4c09-b316-d97b280a6ab3</control-param>
						</control>
					</field>
					<field id="rb:remitente" label-id="prop.rb_remitente" set="datos_oficio" >
						<control template="/org/alfresco/components/form/controls/category.ftl"> 
							<control-param name="parentNodeRef">workspace://SpacesStore/ab0e64a2-96a4-4c09-b316-d97b280a6ab3</control-param>
						</control>
					</field>
					<field id="rb:radicado_ext" label-id="prop.rb_radicado_ext" set="datos_oficio" >
						<control template="/org/alfresco/components/form/controls/textfield.ftl" />
					</field>
					<field id="rb:fecha_radicado" label-id="prop.rb_fecha_radicado" set="datos_oficio" >
						<control template="/org/alfresco/components/form/controls/daterange.ftl" />
					</field>
					<field id="rb:respuesta_req" label-id="prop.rb_respuesta_req" set="datos_oficio" >
						<control template="/org/alfresco/components/form/controls/checkbox.ftl" />
					</field>
					<field id="rb:fecha_resp" label-id="prop.rb_fecha_resp" set="datos_oficio" >
						<control template="/org/alfresco/components/form/controls/daterange.ftl" />
					</field>
					<field id="rb:area_resp" label-id="prop.rb_area_resp" set="datos_oficio" >
						<control template="/org/alfresco/components/form/controls/category.ftl"> 
						<!-- Configuramos la categorìa para que se inicie en el nodo de "Areas de Empresa" -->
							<control-param name="parentNodeRef">workspace://SpacesStore/7b6839e0-4b90-477f-b5aa-de44e415a70a</control-param>
						</control>
					</field>
					<!--
					<field id="rb:persona_resp" label-id="prop.rb_persona_resp" set="datos_oficio" >
						<control template="/org/alfresco/components/form/controls/authority.ftl" />
					</field>
					-->
					<field id="rb:personaResp" label-id="assoc.rb_personaResp" set="datos_oficio" >
						<control template="/org/alfresco/components/form/controls/authority.ftl" />
					</field>
					<field id="rb:respondida" label-id="prop.rb_respondida" set="datos_oficio" >
						<control template="/org/alfresco/components/form/controls/checkbox.ftl" />
					</field>
					<field id="rb:relevancia" label-id="prop.rb_relevancia" set="datos_oficio" >
						<control template="/org/alfresco/components/form/controls/selectone.ftl" >
							<control-param name="options">1|{label.alta},2|{label.media},3|{label.baja}</control-param>
						</control>
					</field>					
					<field id="rb:revisado" label-id="prop.rb_revisado" set="datos_oficio"   >
						<control template="/org/alfresco/components/form/controls/checkbox.ftl" />
					</field>
				</appearance>
			</form>
		</forms>
	</config>				
		


</alfresco-config>